Examples/Keras常用操作.md
Examples/__init__.py
Examples/dnn_baseline.py
Examples/mcdropout.py
Examples/model.png
Examples/pooling.py
Examples/skorch_demo.py
Examples/wandb_example.py
Examples/feature_column/FeatureColumns.py
Examples/feature_column/README.md
Examples/feature_column/__init__.py
Examples/feature_column/demo.py
Examples/muit_inputs/__init__.py
Examples/muit_inputs/demo.py
Examples/muit_inputs/muit_inputs_outputs.py
Tutorials/__init__.py
inn/Require.md
inn/__init__.py
inn/backend.py
inn/demo.py
inn/files.yml
inn/activations/Dice.py
inn/activations/README.md
inn/activations/__init__.py
inn/callbacks/__init__.py
inn/callbacks/wandb_callback.py
inn/callbacks/clr_callbacks/CyclicLR.py
inn/callbacks/clr_callbacks/__init__.py
inn/config/__init__.py
inn/config/config.yml
inn/config/config_utils.py
inn/cv/KerasCV.py
inn/cv/__init__.py
inn/dateset/Dataset.py
inn/dateset/__init__.py
inn/dateset/tfreader.py
inn/dateset/tfrecord_write.py
inn/dateset/utils.py
inn/deploy/README.md
inn/deploy/__init__.py
inn/deploy/serving/__init__.py
inn/deploy/serving/onnx/__init__.py
inn/deploy/serving/onnx/gbtree.onnx
inn/deploy/serving/onnx/inference.py
inn/deploy/serving/onnx/iris.onnx
inn/deploy/serving/onnx/simplifier_onnx.sh
inn/deploy/serving/onnx/torch_convert.py
inn/deploy/serving/onnx/xgb_convert.py
inn/explainer/README.md
inn/explainer/__init__.py
inn/features/__init__.py
inn/features/embedding.py
inn/features/feature_column.py
inn/features/fc/__init__.py
inn/features/fc/utils.py
inn/features/transformer/CountEncoder.py
inn/features/transformer/CountRankEncoder.py
inn/features/transformer/DataAugment.py
inn/features/transformer/GaussRankScaler.py
inn/features/transformer/MultiHot.py
inn/features/transformer/OptimizedRounder.py
inn/features/transformer/OutlierEncoder.py
inn/features/transformer/RankEncoder.py
inn/features/transformer/__init__.py
inn/features/transformer/smooth_utils.py
inn/layers/Add.py
inn-2020.7.14.17.56.58.dist-info/METADATA
inn-2020.7.14.17.56.58.dist-info/RECORD
inn-2020.7.14.17.56.58.dist-info/WHEEL
inn-2020.7.14.17.56.58.dist-info/entry_points.txt
inn-2020.7.14.17.56.58.dist-info/top_level.txt
